[{"id":1,"name":"Shareef","phone":"999","has_accommodation":false,"created_at":"2025-07-05T19:38:50.497Z","updated_at":"2025-07-05T19:38:50.497Z"},{"id":2,"name":"Noufal","phone":"9999","has_accommodation":false,"created_at":"2025-07-05T19:38:50.497Z","updated_at":"2025-07-05T19:38:50.497Z"},{"id":3,"name":"Shaju","phone":"888","has_accommodation":true,"created_at":"2025-07-05T19:38:50.497Z","updated_at":"2025-07-05T19:38:50.497Z"},{"id":4,"name":"Mahesh","phone":"888","has_accommodation":true,"created_at":"2025-07-05T19:38:50.497Z","updated_at":"2025-07-05T19:38:50.497Z"},{"id":5,"name":"Adharsh em","phone":"9999","has_accommodation":false,"created_at":"2025-07-05T19:38:50.497Z","updated_at":"2025-07-05T19:38:50.497Z"},{"id":6,"name":"Adhrash km","phone":"00","has_accommodation":false,"created_at":"2025-07-05T19:38:50.497Z","updated_at":"2025-07-05T19:38:50.497Z"},{"id":7,"name":"alwin","phone":"00","has_accommodation":false,"created_at":"2025-07-05T19:38:50.497Z","updated_at":"2025-07-05T19:38:50.497Z"},{"id":8,"name":"rahul","phone":"000","has_accommodation":false,"created_at":"2025-07-05T19:38:50.497Z","updated_at":"2025-07-05T19:38:50.497Z"},{"id":9,"name":"Basheer","phone":"33","has_accommodation":false,"created_at":"2025-07-05T19:38:50.497Z","updated_at":"2025-07-05T19:38:50.497Z"}]